quantumcrypto/__init__.py
quantumcrypto/ml_kem.py
quantumcrypto/utils/__init__.py
quantumcrypto/utils/functions.py
quantumcrypto/utils/parameters.py
tests/__init__.py
tests/test_byte_encode_decode.py
tests/test_compress_decompress.py
tests/test_encrypt_decrypt.py
tests/test_ghj_func.py
tests/test_inner_functions.py
tests/test_key_gen.py
tests/test_ml_kem_class.py
tests/test_ntt.py
quantumcrypto-0.2.3.dist-info/METADATA
quantumcrypto-0.2.3.dist-info/WHEEL
quantumcrypto-0.2.3.dist-info/top_level.txt
quantumcrypto-0.2.3.dist-info/RECORD
