Metadata-Version: 2.1
Name: quantumcrypto
Version: 0.2.3
Summary: A cryptography library.
Requires-Dist: numpy==2.0.2
Requires-Dist: pycryptodome==3.21.0
